rastreio/__init__.py
rastreio/rastreio.py
rastreio-0.0.3.data/scripts/rastreio.py
rastreio-0.0.3.dist-info/DESCRIPTION.rst
rastreio-0.0.3.dist-info/METADATA
rastreio-0.0.3.dist-info/RECORD
rastreio-0.0.3.dist-info/WHEEL
rastreio-0.0.3.dist-info/entry_points.txt
rastreio-0.0.3.dist-info/metadata.json
rastreio-0.0.3.dist-info/top_level.txt
