Metadata-Version: 2.0
Name: rastreio
Version: 0.0.3
Summary: Utility to track packages in the Brazilian post site
Home-page: http://github.com/utzig/rastreio
Author: Fabio Utzig
Author-email: utzig@utzig.org
License: MIT
Platform: UNKNOWN
Classifier: Development Status :: 3 - Alpha
Classifier: Topic :: Utilities
Classifier: License :: OSI Approved :: MIT License
Requires-Dist: gevent
Requires-Dist: requests
